awsbreaker/__init__.py
awsbreaker/__main__.py
awsbreaker/cli.py
awsbreaker/conf/__init__.py
awsbreaker/conf/config.py
awsbreaker/conf/config.yaml
awsbreaker/core/__init__.py
awsbreaker/core/arn.py
awsbreaker/core/session_helper.py
awsbreaker/logger.py
awsbreaker/main.py
awsbreaker/orchestrator.py
awsbreaker/reporter.py
awsbreaker/services/__init__.py
awsbreaker/services/ec2/__init__.py
awsbreaker/services/ec2/instances.py
awsbreaker/services/ec2/key_pairs.py
awsbreaker-0.1.1.dist-info/WHEEL
awsbreaker-0.1.1.dist-info/entry_points.txt
awsbreaker-0.1.1.dist-info/METADATA
awsbreaker-0.1.1.dist-info/RECORD
