Metadata-Version: 2.3
Name: awsbreaker
Version: 0.1.1
Summary: A kill-switch for AWS that automatically deletes resources when spending limits are breached.
Keywords: aws,budget,cost,cost-control,cleanup,devops,security,utilities
Author: hyperoot
Author-email: hyperoot <rajesh@hyperoot.dev>
License: MIT License
Classifier: Development Status :: 3 - Alpha
Classifier: Environment :: Console
Classifier: Intended Audience :: Developers
Classifier: Intended Audience :: System Administrators
Classifier: Intended Audience :: Information Technology
Classifier: License :: OSI Approved :: MIT License
Classifier: Operating System :: OS Independent
Classifier: Programming Language :: Python
Classifier: Programming Language :: Python :: 3
Classifier: Programming Language :: Python :: 3 :: Only
Classifier: Programming Language :: Python :: 3.13
Classifier: Programming Language :: Python :: 3.14
Classifier: Topic :: System :: Systems Administration
Classifier: Topic :: Utilities
Classifier: Typing :: Typed
Classifier: Natural Language :: English
Requires-Dist: boto3>=1.40.1
Requires-Dist: pyfiglet>=1.0.3
Requires-Dist: pyyaml>=6.0.2
Requires-Dist: rich>=14.1.0
Requires-Dist: typer>=0.16.0
Requires-Python: >=3.13
Project-URL: Homepage, https://github.com/HYP3R00T/awsbreaker
Project-URL: Issues, https://github.com/HYP3R00T/awsbreaker/issues
Project-URL: Repository, https://github.com/HYP3R00T/awsbreaker
